webull/__init__.py
webull/endpoints.py
webull/streamconn.py
webull/webull.py
webull_12-2023.0.2.dist-info/LICENSE
webull_12-2023.0.2.dist-info/METADATA
webull_12-2023.0.2.dist-info/WHEEL
webull_12-2023.0.2.dist-info/top_level.txt
webull_12-2023.0.2.dist-info/RECORD
