Metadata-Version: 2.1
Name: webull-12
Version: 2023.0.2
Summary: The unofficial fork of webull [https://pypi.org/project/webull/]
Home-page: https://github.com/tedchou12/webull.git
License: MIT
Classifier: Programming Language :: Python :: 3
Classifier: License :: OSI Approved :: MIT License
Classifier: Operating System :: OS Independent
Requires-Python: >=3.6
License-File: LICENSE
Requires-Dist: certifi (>=2020.4.5.1)
Requires-Dist: chardet (>=3.0.4)
Requires-Dist: idna (>=2.9)
Requires-Dist: numpy (>=1.18.4)
Requires-Dist: pandas (>=0.25.3)
Requires-Dist: python-dateutil (>=2.8.1)
Requires-Dist: pytz (>=2020.1)
Requires-Dist: requests (>=2.23.0)
Requires-Dist: six (>=1.14.0)
Requires-Dist: urllib3 (>=1.25.9)
Requires-Dist: email-validator (>=1.1.0)
Requires-Dist: paho-mqtt (>=1.6.0)
